blackarrow/__init__.py
blackarrow/blackarrow.py
blackarrow/test/__init__.py
blackarrow/test/test_indexing.py
blackarrow-1.3.2.dist-info/LICENSE.txt
blackarrow-1.3.2.dist-info/METADATA
blackarrow-1.3.2.dist-info/WHEEL
blackarrow-1.3.2.dist-info/entry_points.txt
blackarrow-1.3.2.dist-info/RECORD
