Metadata-Version: 2.1
Name: blackarrow
Version: 1.3.2
Summary: A fast keyword searcher
Home-page: https://github.com/TheDataLeek/black-arrow
License: MIT
Keywords: development,searching,text,find,replace
Author: Zoe Farmer
Author-email: zoe@dataleek.io
Requires-Python: >=3.6.2,<4.0.0
Classifier: Development Status :: 5 - Production/Stable
Classifier: Environment :: Console
Classifier: Intended Audience :: Developers
Classifier: License :: OSI Approved :: MIT License
Classifier: Natural Language :: English
Classifier: Operating System :: Unix
Classifier: Programming Language :: Python :: 3
Classifier: Programming Language :: Python :: 3.7
Classifier: Programming Language :: Python :: 3.8
Classifier: Programming Language :: Python :: 3.9
Classifier: Programming Language :: Python :: 3.10
Classifier: Programming Language :: Python :: 3.11
Classifier: Programming Language :: Python :: 3.12
Classifier: Programming Language :: Python :: 3.5
Classifier: Programming Language :: Python :: 3.6
Requires-Dist: fabulous (>=0.4.0,<0.5.0)
Requires-Dist: faster-fifo (>=1.4.5,<2.0.0)
Project-URL: Repository, https://github.com/TheDataLeek/black-arrow
